{"datasets": [{"metric": "Price", "label": "Price on NSE", "values": [["2023-09-13", "311.95"], ["2023-09-14", "309.75"], ["2023-09-15", "311.35"], ["2023-09-18", "310.10"], ["2023-09-20", "305.50"]], "meta": {"exchange": "nse", "unit": "day"}}, {"metric": "Volume", "label": "Volume", "values": [["2023-09-13", 678766, {"delivery": 27}], ["2023-09-14", 379359, {"delivery": 37}], ["2023-09-15", 376873, {"delivery": 35}], ["2023-09-18", 312639, {"delivery": 33}], ["2023-09-20", 384847, {"delivery": 42}]], "meta": {}}, {"metric": "DMA200", "label": "200 DMA", "values": [["2023-09-13", "247.14"], ["2023-09-14", "247.76"], ["2023-09-15", "248.39"], ["2023-09-18", "249.01"], ["2023-09-20", "249.57"]], "meta": {}}]}