{"datasets": [{"metric": "Price", "label": "Price on NSE", "values": [["2023-09-13", "476.85"], ["2023-09-14", "488.90"], ["2023-09-15", "487.50"], ["2023-09-18", "476.60"], ["2023-09-20", "470.15"]], "meta": {"exchange": "nse", "unit": "day"}}, {"metric": "Volume", "label": "Volume", "values": [["2023-09-13", 111193, {"delivery": 33}], ["2023-09-14", 66412, {"delivery": 30}], ["2023-09-15", 87785, {"delivery": 28}], ["2023-09-18", 92013, {"delivery": 26}], ["2023-09-20", 81130, {"delivery": 29}]], "meta": {}}, {"metric": "DMA200", "label": "200 DMA", "values": [["2023-09-13", "428.54"], ["2023-09-14", "429.14"], ["2023-09-15", "429.72"], ["2023-09-18", "430.19"], ["2023-09-20", "430.58"]], "meta": {}}]}