{"datasets": [{"metric": "Price", "label": "Price on NSE", "values": [["2023-09-15", "485.30"], ["2023-09-18", "473.60"], ["2023-09-20", "488.95"], ["2023-09-21", "487.65"], ["2023-09-22", "481.80"]], "meta": {"exchange": "nse", "unit": "day"}}, {"metric": "Volume", "label": "Volume", "values": [["2023-09-15", 2437464, {"delivery": 72}], ["2023-09-18", 550384, {"delivery": 56}], ["2023-09-20", 603509, {"delivery": 41}], ["2023-09-21", 352035, {"delivery": 56}], ["2023-09-22", 240670, {"delivery": 49}]], "meta": {}}, {"metric": "DMA200", "label": "200 DMA", "values": [["2023-09-15", "388.52"], ["2023-09-18", "389.37"], ["2023-09-20", "390.36"], ["2023-09-21", "391.32"], ["2023-09-22", "392.23"]], "meta": {}}]}