{"datasets": [{"metric": "Price", "label": "Price on NSE", "values": [["2023-09-14", "416.90"], ["2023-09-15", "422.20"], ["2023-09-18", "413.60"], ["2023-09-20", "413.80"], ["2023-09-21", "406.60"], ["2023-09-22", "405.40"]], "meta": {"exchange": "nse", "unit": "day"}}, {"metric": "Volume", "label": "Volume", "values": [["2023-09-14", 844334, {"delivery": 38}], ["2023-09-15", 389759, {"delivery": 50}], ["2023-09-18", 253627, {"delivery": 46}], ["2023-09-20", 349157, {"delivery": 31}], ["2023-09-21", 246132, {"delivery": 48}], ["2023-09-22", 81209, {"delivery": null}]], "meta": {}}, {"metric": "DMA200", "label": "200 DMA", "values": [["2023-09-14", "372.20"], ["2023-09-15", "372.70"], ["2023-09-18", "373.10"], ["2023-09-20", "373.51"], ["2023-09-21", "373.84"], ["2023-09-22", "374.15"]], "meta": {}}]}