{"datasets": [{"metric": "Price", "label": "Price on NSE", "values": [["2023-09-15", "131.85"], ["2023-09-18", "132.20"], ["2023-09-20", "133.10"], ["2023-09-21", "129.30"], ["2023-09-22", "129.90"]], "meta": {"exchange": "nse", "unit": "day"}}, {"metric": "Volume", "label": "Volume", "values": [["2023-09-15", 1714880, {"delivery": 48}], ["2023-09-18", 1819843, {"delivery": 46}], ["2023-09-20", 2082928, {"delivery": 52}], ["2023-09-21", 894658, {"delivery": 46}], ["2023-09-22", 1201359, {"delivery": 38}]], "meta": {}}, {"metric": "DMA200", "label": "200 DMA", "values": [["2023-09-15", "100.74"], ["2023-09-18", "101.06"], ["2023-09-20", "101.38"], ["2023-09-21", "101.65"], ["2023-09-22", "101.93"]], "meta": {}}]}