{"datasets": [{"metric": "Price", "label": "Price on NSE", "values": [["2023-09-14", "967.20"], ["2023-09-15", "963.10"], ["2023-09-18", "986.60"], ["2023-09-20", "958.45"], ["2023-09-21", "944.60"], ["2023-09-22", "954.35"]], "meta": {"exchange": "nse", "unit": "day"}}, {"metric": "Volume", "label": "Volume", "values": [["2023-09-14", 9988, {"delivery": 47}], ["2023-09-15", 22794, {"delivery": 49}], ["2023-09-18", 113353, {"delivery": 43}], ["2023-09-20", 31788, {"delivery": 41}], ["2023-09-21", 25250, {"delivery": 39}], ["2023-09-22", 6508, {"delivery": null}]], "meta": {}}, {"metric": "DMA200", "label": "200 DMA", "values": [["2023-09-14", "566.32"], ["2023-09-15", "570.26"], ["2023-09-18", "574.41"], ["2023-09-20", "578.23"], ["2023-09-21", "581.87"], ["2023-09-22", "585.58"]], "meta": {}}]}