{"datasets": [{"metric": "Price", "label": "Price on NSE", "values": [["2023-09-15", "163.10"], ["2023-09-18", "160.80"], ["2023-09-20", "155.85"], ["2023-09-21", "152.75"], ["2023-09-22", "153.45"]], "meta": {"exchange": "nse", "unit": "day"}}, {"metric": "Volume", "label": "Volume", "values": [["2023-09-15", 1171856, {"delivery": 43}], ["2023-09-18", 471585, {"delivery": 49}], ["2023-09-20", 405460, {"delivery": 46}], ["2023-09-21", 370604, {"delivery": 41}], ["2023-09-22", 243192, {"delivery": 37}]], "meta": {}}, {"metric": "DMA200", "label": "200 DMA", "values": [["2023-09-15", "132.87"], ["2023-09-18", "133.15"], ["2023-09-20", "133.38"], ["2023-09-21", "133.57"], ["2023-09-22", "133.77"]], "meta": {}}]}